Workbook

Sheet Overview
B2: biolyt.ai | Expanded Persona Question Catalog
B3: Full question library across personas and complexity tiers, with a dedicated competitive intelligence set. Slots in [brackets] are user-filled.
B5: Counts by persona and tier
B6: Persona | C6: Simple | D6: Medium | E6: Complex | F6: Total | G6: CI | H6: Focus
B7: Safety & PV | C7: =COUNTIF('Safety & PV'!$B:$B,"Simple") -> 7 | D7: =COUNTIF('Safety & PV'!$B:$B,"Medium") -> 7 | E7: =COUNTIF('Safety & PV'!$B:$B,"Complex") -> 6 | F7: =SUM(C7:E7) -> 20 | G7: =COUNTIF('Safety & PV'!$H:$H,"Yes") -> 2 | H7: Pharmacovigilance, signal detection, case management
B8: Medical Affairs | C8: =COUNTIF('Medical Affairs'!$B:$B,"Simple") -> 7 | D8: =COUNTIF('Medical Affairs'!$B:$B,"Medium") -> 7 | E8: =COUNTIF('Medical Affairs'!$B:$B,"Complex") -> 6 | F8: =SUM(C8:E8) -> 20 | G8: =COUNTIF('Medical Affairs'!$H:$H,"Yes") -> 8 | H8: Scientific evidence, MSL support, competitive intelligence
B9: Clinical Operations | C9: =COUNTIF('Clinical Operations'!$B:$B,"Simple") -> 7 | D9: =COUNTIF('Clinical Operations'!$B:$B,"Medium") -> 7 | E9: =COUNTIF('Clinical Operations'!$B:$B,"Complex") -> 6 | F9: =SUM(C9:E9) -> 20 | G9: =COUNTIF('Clinical Operations'!$H:$H,"Yes") -> 1 | H9: Site performance, enrollment, protocol conduct
B10: Data Management | C10: =COUNTIF('Data Management'!$B:$B,"Simple") -> 7 | D10: =COUNTIF('Data Management'!$B:$B,"Medium") -> 7 | E10: =COUNTIF('Data Management'!$B:$B,"Complex") -> 5 | F10: =SUM(C10:E10) -> 19 | G10: =COUNTIF('Data Management'!$H:$H,"Yes") -> 0 | H10: Query resolution, discrepancies, database quality
B11: Regulatory Affairs | C11: =COUNTIF('Regulatory Affairs'!$B:$B,"Simple") -> 7 | D11: =COUNTIF('Regulatory Affairs'!$B:$B,"Medium") -> 6 | E11: =COUNTIF('Regulatory Affairs'!$B:$B,"Complex") -> 5 | F11: =SUM(C11:E11) -> 18 | G11: =COUNTIF('Regulatory Affairs'!$H:$H,"Yes") -> 3 | H11: Submissions, labeling, evidence traceability
B12: Clinical Leadership | C12: =COUNTIF('Clinical Leadership'!$B:$B,"Simple") -> 7 | D12: =COUNTIF('Clinical Leadership'!$B:$B,"Medium") -> 6 | E12: =COUNTIF('Clinical Leadership'!$B:$B,"Complex") -> 6 | F12: =SUM(C12:E12) -> 19 | G12: =COUNTIF('Clinical Leadership'!$H:$H,"Yes") -> 2 | H12: Portfolio delivery, risk, executive reporting
B13: Competitive Intelligence (tab) | C13: =COUNTIF('Competitive Intelligence'!$B:$B,"Simple") -> 6 | D13: =COUNTIF('Competitive Intelligence'!$B:$B,"Medium") -> 6 | E13: =COUNTIF('Competitive Intelligence'!$B:$B,"Complex") -> 6 | F13: =SUM(C13:E13) -> 18 | G13: =F13 -> 18 | H13: Cross-persona competitive intelligence
B14: Total | C14: =SUM(C7:C13) -> 48 | D14: =SUM(D7:D13) -> 46 | E14: =SUM(E7:E13) -> 40 | F14: =SUM(F7:F13) -> 134 | G14: =SUM(G7:G13) -> 34
B16: Note: CI counts the questions tagged for competitive intelligence within each persona tab. The Competitive Intelligence tab is an additional curated cross-persona set.

Sheet Safety & PV
A1: Safety & PV
A2: Pharmacovigilance, signal detection, case management
A4: ID | B4: Complexity | C4: Persona Question (card label) | D4: Role Activity Supported | E4: Corpus Data Leveraged | F4: Answer Format / Output | G4: Agent Reasoning Depth | H4: CI
A5: 1 | B5: Simple | C5: Show all serious adverse events for [product] in the last 30 days | D5: Daily surveillance | E5: ICSRs, seriousness flags, receipt dates | F5: Filtered case table | G5: Single retrieval + filter
A6: 2 | B6: Simple | C6: List cases matching preferred term [PT] filed this quarter | D6: Case triage | E6: Coded MedDRA terms, case metadata | F6: Case list with links | G6: Single retrieval + filter
A7: 3 | B7: Simple | C7: How many cases are pending medical review right now? | D7: Backlog check | E7: Case status, workflow state | F7: Count with drill-down | G7: Count / aggregate
A8: 4 | B8: Simple | C8: List all fatal case reports for [product] year to date | D8: Fatal case oversight | E8: Outcome fields, case records | F8: Case list | G8: Filtered retrieval
A9: 5 | B9: Simple | C9: Show cases received from [country/region] this week | D9: Regional intake review | E9: Case origin, receipt dates | F9: Filtered list | G9: Single retrieval + filter
A10: 6 | B10: Simple | C10: Which cases are approaching their 15-day reporting deadline? | D10: Reportability tracking | E10: Reportability clocks, case status | F10: Deadline queue | G10: Filter + date logic
A11: 7 | B11: Simple | C11: Pull all cases involving [concomitant medication] | D11: Interaction screening | E11: Concomitant med fields | F11: Case list | G11: Filtered retrieval
A12: 8 | B12: Medium | C12: Summarize the AE profile for [product] by seriousness and causality | D12: Periodic review prep | E12: ICSRs, causality, outcomes | F12: Cross-tab + chart | G12: Aggregation + summarization
A13: 9 | B13: Medium | C13: Are there emerging signals across these PTs vs baseline in the last 90 days? | D13: Signal monitoring | E13: Case volumes, baselines, PT groups | F13: Trend view with flags | G13: Comparative trend analysis
A14: 10 | B14: Medium | C14: Show case volume trend by geography and reporting source for [product] | D14: Reporting pattern review | E14: Case origin, reporter type, time series | F14: Trend chart by segment | G14: Multi-dimension aggregation
A15: 11 | B15: Medium | C15: Break down adverse events by System Organ Class for [product] | D15: AE profiling | E15: SOC hierarchy, coded events | F15: SOC distribution chart | G15: Aggregation + grouping
A16: 12 | B16: Medium | C16: Summarize case outcomes for [PT] over the last year | D16: Outcome analysis | E16: Outcome fields, time series | F16: Outcome summary | G16: Aggregation + summarization
A17: 13 | B17: Medium | C17: Identify events most frequently co-reported with [PT] | D17: Co-occurrence analysis | E17: Multi-event case records | F17: Co-occurrence ranking | G17: Association analysis
A18: 14 | B18: Medium | C18: Monitor class-wide safety signals for [therapeutic class] across products | D18: Class safety monitoring | E18: Competitor and class case patterns | F18: Class signal view | G18: Comparative trend analysis | H18: Yes
A19: 15 | B19: Complex | C19: Detect disproportionality signals for [product] and rank by strength of association | D19: Quantitative detection | E19: Full case corpus, exposure denominators | F19: Ranked signal table | G19: Statistical + multi-step reasoning
A20: 16 | B20: Complex | C20: Draft a signal evaluation summary for [PT]: narratives, temporal pattern, confounders | D20: Signal workup | E20: Narratives, timelines, concomitant meds | F20: Draft evaluation doc | G20: Synthesis + document generation
A21: 17 | B21: Complex | C21: Assess whether the AE pattern for [product] warrants a label update, with supporting cases | D21: Labeling decision support | E21: Case corpus, comparator evidence, label | F21: Assessment memo | G21: Causal reasoning + recommendation
A22: 18 | B22: Complex | C22: Generate the safety section narrative for the PSUR/PBRER for [product] | D22: Aggregate report authoring | E22: Case data, literature, prior reports | F22: Draft report section | G22: Synthesis + document generation
A23: 19 | B23: Complex | C23: Build a benefit-risk summary for [product] integrating efficacy and safety evidence | D23: Benefit-risk assessment | E23: Efficacy, safety, comparator data | F23: Benefit-risk summary | G23: Cross-domain synthesis
A24: 20 | B24: Complex | C24: Compare the safety profile of [product] against [competitor product] | D24: Comparative safety CI | E24: Case corpus, competitor safety data | F24: Comparison + narrative | G24: Cross-source synthesis | H24: Yes

Sheet Medical Affairs
A1: Medical Affairs
A2: Scientific evidence, MSL support, competitive intelligence
A4: ID | B4: Complexity | C4: Persona Question (card label) | D4: Role Activity Supported | E4: Corpus Data Leveraged | F4: Answer Format / Output | G4: Agent Reasoning Depth | H4: CI
A5: 1 | B5: Simple | C5: Find published evidence supporting [claim] for [indication] | D5: Evidence lookup | E5: Publications, trial results | F5: Citation list | G5: Single retrieval + filter
A6: 2 | B6: Simple | C6: List active competitor trials for [indication] | D6: Competitive awareness | E6: Registry records, phase fields | F6: Trial list | G6: Filtered retrieval | H6: Yes
A7: 3 | B7: Simple | C7: Pull the latest efficacy data for [product] in [subpopulation] | D7: Fast fact retrieval | E7: Trial endpoints, subgroup results | F7: Endpoint card | G7: Filtered retrieval
A8: 4 | B8: Simple | C8: Show recent congress abstracts mentioning [product] | D8: Congress tracking | E8: Abstracts, presentation metadata | F8: Abstract list | G8: Filtered retrieval
A9: 5 | B9: Simple | C9: List key opinion leaders publishing on [indication] | D9: KOL mapping | E9: Author records, publication data | F9: KOL list | G9: Retrieval + grouping
A10: 6 | B10: Simple | C10: What is the approved dosing for [product] in [indication]? | D10: Label reference | E10: Approved label data | F10: Dosing card | G10: Single retrieval
A11: 7 | B11: Simple | C11: Find the most recent real-world evidence study on [product] | D11: RWE lookup | E11: RWE study corpus | F11: Study summary | G11: Filtered retrieval
A12: 8 | B12: Medium | C12: Summarize the evidence base for an MSL response to [scientific question] | D12: MSL response prep | E12: Publications, trials, congress data | F12: Evidence summary | G12: Aggregation + summarization
A13: 9 | B13: Medium | C13: Compare [product] vs [comparator] across efficacy and safety endpoints | D13: Comparative positioning | E13: Cross-trial endpoint data | F13: Comparison table | G13: Cross-source comparison | H13: Yes
A14: 10 | B14: Medium | C14: Map the competitive trial landscape for [indication] by phase, mechanism, sponsor | D14: Landscape monitoring | E14: Registry data, mechanism tags | F14: Landscape matrix | G14: Multi-dimension synthesis | H14: Yes
A15: 11 | B15: Medium | C15: Summarize mechanism-of-action differences between [product] and [comparator] | D15: Scientific differentiation | E15: MoA literature, trial data | F15: MoA comparison | G15: Cross-source comparison | H15: Yes
A16: 12 | B16: Medium | C16: Track how evidence for [claim] has evolved over the last three years | D16: Evidence trend | E16: Publication time series | F16: Evidence timeline | G16: Temporal synthesis
A17: 13 | B17: Medium | C17: Identify the top unanswered scientific questions from recent KOL interactions | D17: Insight synthesis | E17: Interaction records, evidence gaps | F17: Ranked question list | G17: Gap analysis
A18: 14 | B18: Medium | C18: Summarize congress coverage for [indication] from the last major meeting | D18: Congress synthesis | E18: Abstracts, presentations | F18: Congress digest | G18: Aggregation + summarization | H18: Yes
A19: 15 | B19: Complex | C19: Draft an evidence-backed scientific response to [KOL question], with citations and gap flags | D19: Inquiry response | E19: Literature corpus, trial data | F19: Draft response | G19: Synthesis + document generation
A20: 16 | B20: Complex | C20: Synthesize a publication gap analysis and recommend priority topics | D20: Publication planning | E20: Publication corpus, competitor output | F20: Gap analysis + plan | G20: Gap reasoning + recommendation
A21: 17 | B21: Complex | C21: Build a payer-ready value narrative integrating clinical, RWE, and comparative evidence | D21: Value communication | E21: Trials, RWE, HEOR, comparator data | F21: Value narrative | G21: Cross-domain synthesis | H21: Yes
A22: 18 | B22: Complex | C22: Generate a competitive positioning brief for [product] vs the [indication] landscape | D22: Positioning | E22: Full evidence + competitor corpus | F22: Positioning brief | G22: Cross-domain synthesis | H22: Yes
A23: 19 | B23: Complex | C23: Build an evidence dossier for [indication] structured for advisory board discussion | D23: Advisory board prep | E23: Trials, publications, RWE | F23: Structured dossier | G23: Synthesis + document generation
A24: 20 | B24: Complex | C24: Analyze where competitor evidence is strongest and recommend a defensive data strategy | D24: Strategic CI | E24: Competitor evidence, own data gaps | F24: Strategy recommendation | G24: Gap reasoning + recommendation | H24: Yes

Sheet Clinical Operations
A1: Clinical Operations
A2: Site performance, enrollment, protocol conduct
A4: ID | B4: Complexity | C4: Persona Question (card label) | D4: Role Activity Supported | E4: Corpus Data Leveraged | F4: Answer Format / Output | G4: Agent Reasoning Depth | H4: CI
A5: 1 | B5: Simple | C5: Which sites are behind enrollment target for [study]? | D5: Enrollment tracking | E5: Enrollment counts, targets | F5: Ranked site list | G5: Filter + threshold
A6: 2 | B6: Simple | C6: Show open protocol deviations for [study] by site | D6: Deviation monitoring | E6: Deviation records, site mapping | F6: Deviation table | G6: Filtered retrieval
A7: 3 | B7: Simple | C7: List sites with no screening activity in the last 14 days | D7: Dormant-site check | E7: Screening logs, timestamps | F7: Flagged site list | G7: Filter + recency logic
A8: 4 | B8: Simple | C8: What is current total enrollment vs target for [study]? | D8: Status check | E8: Enrollment counts, plan | F8: Progress figure | G8: Count / aggregate
A9: 5 | B9: Simple | C9: Show screen-fail rate by site for [study] | D9: Screening review | E9: Screening and enrollment logs | F9: Rate by site | G9: Rate calculation
A10: 6 | B10: Simple | C10: List sites still pending activation for [study] | D10: Startup tracking | E10: Activation status records | F10: Pending site list | G10: Filtered retrieval
A11: 7 | B11: Simple | C11: Which sites have the longest data entry lag? | D11: Data timeliness check | E11: Entry timestamps vs visit dates | F11: Ranked site list | G11: Filter + ranking
A12: 8 | B12: Medium | C12: Show enrollment trajectory vs plan for [study] and flag at-risk sites | D12: Enrollment risk review | E12: Enrollment time series, planned curve | F12: Trajectory chart + flags | G12: Trend + variance analysis
A13: 9 | B13: Medium | C13: Cluster protocol deviations by type and site for [study] | D13: Pattern spotting | E13: Deviation categories, site attributes | F13: Cluster view | G13: Grouping + pattern detection
A14: 10 | B14: Medium | C14: Compare site performance across screen-fail, velocity, and query burden | D14: Site benchmarking | E14: Screening, enrollment, query data | F14: Multi-metric scorecard | G14: Cross-metric aggregation
A15: 11 | B15: Medium | C15: Rank sites by overall performance for [study] | D15: Site ranking | E15: Composite site metrics | F15: Ranked list | G15: Weighted scoring
A16: 12 | B16: Medium | C16: Show enrollment by month and project the current run rate | D16: Run-rate projection | E16: Enrollment time series | F16: Trend + projection | G16: Trend extrapolation
... A23: 19 | B23: Complex | C23: Forecast the impact of adding [n] new sites on the enrollment timeline | D23: Scenario planning | E23: Site ramp curves, capacity | F23: Scenario forecast | G23: Predictive modeling
A24: 20 | B24: Complex | C24: Assess feasibility for a planned [indication] study using site history and competing trials | D24: Feasibility assessment | E24: Site history, competing-trial data | F24: Feasibility brief | G24: Cross-domain synthesis | H24: Yes

Sheet Data Management
A1: Data Management
A2: Query resolution, discrepancies, database quality
A4: ID | B4: Complexity | C4: Persona Question (card label) | D4: Role Activity Supported | E4: Corpus Data Leveraged | F4: Answer Format / Output | G4: Agent Reasoning Depth | H4: CI
A5: 1 | B5: Simple | C5: Show outstanding queries for [study] by site and aging bucket | D5: Backlog tracking | E5: Query records, open dates | F5: Aging table | G5: Aggregation + bucketing
A6: 2 | B6: Simple | C6: How many discrepancies are open on [form/CRF]? | D6: Form status check | E6: Discrepancy records, form IDs | F6: Count with drill-down | G6: Count / filter
A7: 3 | B7: Simple | C7: List subjects with missing critical data fields for [study] | D7: Completeness check | E7: CRF data, critical-field defs | F7: Subject list | G7: Filter + null detection
A8: 4 | B8: Simple | C8: Show total open vs closed queries for [study] | D8: Query status | E8: Query status records | F8: Open/closed summary | G8: Count / aggregate
A9: 5 | B9: Simple | C9: Which forms have the most open queries? | D9: Form-level triage | E9: Query records by form | F9: Ranked form list | G9: Aggregation + ranking
A10: 6 | B10: Simple | C10: List queries open longer than [n] days | D10: Aging triage | E10: Query open dates | F10: Aged query list | G10: Filter + date logic
A11: 7 | B11: Simple | C11: Show the medical coding backlog for [study] | D11: Coding status | E11: Coding queue, term records | F11: Backlog summary | G11: Count / aggregate
A12: 8 | B12: Medium | C12: Show query rate anomalies by form and site for [study] | D12: Anomaly surveillance | E12: Query volumes, baselines | F12: Anomaly heatmap | G12: Comparative anomaly detection
A13: 9 | B13: Medium | C13: Summarize the discrepancy aging report and flag SLA breaches | D13: SLA governance | E13: Aging data, SLA thresholds | F13: Aging summary + flags | G13: Aggregation + threshold logic
A14: 10 | B14: Medium | C14: Identify forms with the highest edit-check failure rate across [study] | D14: CRF quality review | E14: Edit-check logs, form metadata | F14: Ranked form list | G14: Rate + ranking
A15: 11 | B15: Medium | C15: Show query resolution velocity trend for [study] | D15: Velocity monitoring | E15: Query open/close time series | F15: Velocity trend | G15: Trend analysis
A16: 12 | B16: Medium | C16: Compare query burden across sites relative to enrollment | D16: Normalized benchmarking | E16: Queries, enrollment counts | F16: Normalized comparison | G16: Cross-metric aggregation
... A23: 19 | B23: Complex | C23: Detect potential data integrity anomalies (outliers, digit preference, duplicates) | D23: Integrity screening | E23: Value distributions across corpus | F23: Anomaly report | G23: Statistical anomaly detection

Sheet Regulatory Affairs
A1: Regulatory Affairs
A2: Submissions, labeling, evidence traceability
A4: ID | B4: Complexity | C4: Persona Question (card label) | D4: Role Activity Supported | E4: Corpus Data Leveraged | F4: Answer Format / Output | G4: Agent Reasoning Depth | H4: CI
A5: 1 | B5: Simple | C5: List evidence supporting [claim] for submission module [X] | D5: Evidence sourcing | E5: Study results, module mapping | F5: Evidence list | G5: Filtered retrieval
A6: 2 | B6: Simple | C6: Show all studies contributing to the [indication] submission | D6: Submission scoping | E6: Study registry, linkage | F6: Study inventory | G6: Single retrieval
A7: 3 | B7: Simple | C7: Pull the current labeling claims for [product] | D7: Label reference | E7: Approved label, claim records | F7: Claim list | G7: Single retrieval
A8: 4 | B8: Simple | C8: What are the open regulatory commitments for [product]? | D8: Commitment check | E8: Commitment records, due dates | F8: Commitment list | G8: Filtered retrieval
A9: 5 | B9: Simple | C9: Show the submission status for [indication] by module | D9: Status check | E9: Module status records | F9: Status view | G9: Aggregation
A10: 6 | B10: Simple | C10: List health authority questions received for [product] this cycle | D10: HA question tracking | E10: HA correspondence records | F10: Question list | G10: Filtered retrieval
A11: 7 | B11: Simple | C11: Find the source study for [specific labeling statement] | D11: Traceability lookup | E11: Label-to-evidence mapping | F11: Source reference | G11: Single retrieval
A12: 8 | B12: Medium | C12: Run a cross-study consistency check for [labeling claim] | D12: Claim substantiation | E12: Endpoint data across studies | F12: Consistency matrix | G12: Cross-source comparison
A13: 9 | B13: Medium | C13: Identify evidence gaps for submission module [X] | D13: Readiness review | E13: Module requirements, evidence | F13: Gap list + severity | G13: Requirement-to-evidence mapping
A14: 10 | B14: Medium | C14: Summarize the safety data package status across contributing studies | D14: Package tracking | E14: Safety datasets, study status | F14: Status summary | G14: Aggregation + rollup
A15: 11 | B15: Medium | C15: Compare [product] labeling against [competitor product] labeling | D15: Label benchmarking | E15: Approved labels, indications | F15: Label comparison | G15: Cross-source comparison | H15: Yes
A16: 12 | B16: Medium | C16: Summarize how [guidance change] affects the current submission | D16: Intelligence review | E16: Guidance text, submission content | F16: Impact summary | G16: Mapping + summarization | H16: Yes
A17: 13 | B17: Medium | C17: Map each labeling claim to its supporting evidence and flag weak links | D17: Substantiation audit | E17: Claims, evidence, strength | F17: Claim-evidence map | G17: Mapping + gap analysis
A18: 14 | B18: Complex | C18: Assess submission readiness for [indication] and flag gaps, inconsistencies, missing datasets | D18: Go/no-go review | E18: Full evidence corpus, requirements | F18: Readiness assessment | G18: Multi-step gap reasoning
A19: 15 | B19: Complex | C19: Draft the clinical overview narrative integrating efficacy and safety, with source traceability | D19: Document authoring | E19: Efficacy, safety, study data | F19: Draft narrative | G19: Synthesis + document generation
A20: 16 | B20: Complex | C20: Model the regulatory impact of [emerging safety signal] on active and planned submissions | D20: Impact planning | E20: Signal data, submission pipeline | F20: Impact assessment | G20: Scenario reasoning + recommendation
A21: 17 | B21: Complex | C21: Analyze approval precedents for [indication] and recommend a regulatory strategy | D21: Strategy CI | E21: Competitor regulatory histories | F21: Strategy recommendation | G21: Precedent synthesis + recommendation | H21: Yes
A22: 18 | B22: Complex | C22: Draft responses to health authority questions using evidence from the corpus | D22: HA response | E22: HA questions, evidence base | F22: Draft responses | G22: Synthesis + document generation

Sheet Clinical Leadership
A1: Clinical Leadership
A2: Portfolio delivery, risk, executive reporting
A4: ID | B4: Complexity | C4: Persona Question (card label) | D4: Role Activity Supported | E4: Corpus Data Leveraged | F4: Answer Format / Output | G4: Agent Reasoning Depth | H4: CI
A5: 1 | B5: Simple | C5: Show milestone status across all active studies | D5: Portfolio status | E5: Milestones, planned vs actual | F5: Milestone dashboard | G5: Aggregation
A6: 2 | B6: Simple | C6: Which studies are behind schedule this quarter? | D6: Delay spotting | E6: Timeline data, baselines | F6: Flagged study list | G6: Filter + threshold
A7: 3 | B7: Simple | C7: List total enrolled subjects across the portfolio | D7: Headline metric | E7: Enrollment across studies | F7: Rolled-up figure | G7: Count / aggregate
A8: 4 | B8: Simple | C8: Show budget vs actual across active programs | D8: Budget check | E8: Budget and spend data | F8: Variance table | G8: Aggregation
A9: 5 | B9: Simple | C9: Which studies have the highest open risk count? | D9: Risk triage | E9: Risk registers by study | F9: Ranked study list | G9: Aggregation + ranking
A10: 6 | B10: Simple | C10: List upcoming milestones in the next 90 days | D10: Look-ahead | E10: Milestone dates | F10: Milestone queue | G10: Filter + date logic
A11: 7 | B11: Simple | C11: Show resource allocation by program | D11: Resourcing check | E11: Assignment data | F11: Allocation view | G11: Aggregation
A12: 8 | B12: Medium | C12: Show a portfolio-level risk rollup across active studies | D12: Risk oversight | E12: Study-level risk indicators | F12: Risk heatmap | G12: Multi-study aggregation
A13: 9 | B13: Medium | C13: Compare timeline slippage across programs and identify the biggest drivers | D13: Delay analysis | E13: Milestone variances, causes | F13: Slippage ranking | G13: Comparative + attribution
A14: 10 | B14: Medium | C14: Summarize resourcing pressure by phase and therapeutic area | D14: Capacity planning | E14: Workload, assignments | F14: Pressure heatmap | G14: Cross-dimension aggregation
A15: 11 | B15: Medium | C15: Show which programs are trending over budget and why | D15: Budget analysis | E15: Spend trends, drivers | F15: Trend + drivers | G15: Trend + attribution
A16: 12 | B16: Medium | C16: Compare delivery performance across CROs and vendors | D16: Vendor benchmarking | E16: Vendor delivery metrics | F16: Vendor comparison | G16: Cross-source comparison
... A21: 17 | B21: Complex | C21: Model the portfolio impact of accelerating [program] vs holding | D21: Investment decision | E21: Program trajectories, dependencies | F21: Scenario comparison | G21: Scenario modeling
A22: 18 | B22: Complex | C22: Assess competitive positioning of the pipeline against landscape development timelines | D22: Strategic CI | E22: Own pipeline, competitor timelines | F22: Positioning assessment | G22: Cross-domain synthesis | H22: Yes
A23: 19 | B23: Complex | C23: Recommend program prioritization based on risk, value, and competitive timing | D23: Portfolio strategy | E23: Risk, value, competitive data | F23: Prioritization + rationale | G23: Optimization + recommendation | H23: Yes

Sheet Competitive Intelligence
A1: Competitive Intelligence
A2: Curated cross-persona CI questions over the same corpus
A4: ID | B4: Complexity | C4: Persona Question (card label) | D4: Role Activity Supported | E4: Corpus Data Leveraged | F4: Answer Format / Output | G4: Agent Reasoning Depth
A5: 1 | B5: Simple | C5: List all active competitor trials for [indication] | D5: Landscape scan | E5: Registry records | F5: Trial list | G5: Filtered retrieval
A6: 2 | B6: Simple | C6: Which competitors have products approved for [indication]? | D6: Approval scan | E6: Approval records | F6: Product list | G6: Single retrieval
A7: 3 | B7: Simple | C7: Show recent competitor trial readouts for [therapeutic class] | D7: Readout tracking | E7: Trial results corpus | F7: Readout list | G7: Filtered retrieval
A8: 4 | B8: Simple | C8: Find the latest label changes for [competitor product] | D8: Label watch | E8: Label change records | F8: Change summary | G8: Filtered retrieval
A9: 5 | B9: Simple | C9: List competitor congress presentations on [indication] this year | D9: Congress watch | E9: Abstracts, presentations | F9: Presentation list | G9: Filtered retrieval
A10: 6 | B10: Simple | C10: What is the phase and status of [competitor asset]? | D10: Asset check | E10: Pipeline records | F10: Status card | G10: Single retrieval
A11: 7 | B11: Medium | C11: Map the competitive pipeline for [indication] by phase, mechanism, and sponsor | D11: Pipeline mapping | E11: Registry, mechanism tags | F11: Pipeline matrix | G11: Multi-dimension synthesis
A12: 8 | B12: Medium | C12: Compare efficacy and safety endpoints for [product] vs [competitor product] | D12: Head-to-head compare | E12: Cross-trial endpoint data | F12: Comparison table | G12: Cross-source comparison
A13: 9 | B13: Medium | C13: Track competitor development timelines and projected readouts for [indication] | D13: Timeline tracking | E13: Milestones, projected dates | F13: Timeline view | G13: Temporal synthesis
A14: 10 | B14: Medium | C14: Summarize the competitive evidence landscape for [claim] | D14: Evidence landscape | E14: Publication + trial corpus | F14: Landscape summary | G14: Aggregation + synthesis
A15: 11 | B15: Medium | C15: Compare labeling and indications across [product] and key competitors | D15: Label comparison | E15: Approved labels | F15: Comparison matrix | G15: Cross-source comparison
A16: 12 | B16: Medium | C16: Show competitor enrollment footprint overlapping [study] sites | D16: Enrollment competition | E16: Site participation data | F16: Overlap heatmap | G16: Geospatial aggregation
... A22: 18 | B22: Complex | C22: Build a BD and licensing landscape scan for [therapeutic area] with gap and threat analysis | D22: BD support | E22: Asset, sponsor, mechanism data | F22: Landscape dossier | G22: Cross-domain synthesis
